rd_client/__init__.py
rd_client/client.py
rd_client/errors.py
rd_client-0.1.5.dist-info/LICENSE
rd_client-0.1.5.dist-info/WHEEL
rd_client-0.1.5.dist-info/METADATA
rd_client-0.1.5.dist-info/RECORD
